intracktive/__about__.py
intracktive/__init__.py
intracktive/__main__.py
intracktive/conftest.py
intracktive/convert.py
intracktive/createHash.py
intracktive/geff.py
intracktive/main.py
intracktive/napari.yaml
intracktive/open.py
intracktive/server.py
intracktive/widget.py
intracktive/_tests/test_cli.py
intracktive/_tests/test_convert.py
intracktive/_tests/test_geff.py
intracktive/_tests/test_widget.py
intracktive/_tests/data/gt_data_bundle.zarr/.zgroup
intracktive/_tests/data/gt_data_bundle.zarr/points/.zarray
intracktive/_tests/data/gt_data_bundle.zarr/points/.zattrs
intracktive/_tests/data/gt_data_bundle.zarr/points/0.0
intracktive/_tests/data/gt_data_bundle.zarr/points/1.0
intracktive/_tests/data/gt_data_bundle.zarr/points_to_tracks/.zattrs
intracktive/_tests/data/gt_data_bundle.zarr/points_to_tracks/.zgroup
intracktive/_tests/data/gt_data_bundle.zarr/points_to_tracks/indices/.zarray
intracktive/_tests/data/gt_data_bundle.zarr/points_to_tracks/indices/0
intracktive/_tests/data/gt_data_bundle.zarr/points_to_tracks/indptr/.zarray
intracktive/_tests/data/gt_data_bundle.zarr/points_to_tracks/indptr/0
intracktive/_tests/data/gt_data_bundle.zarr/tracks_to_points/.zattrs
intracktive/_tests/data/gt_data_bundle.zarr/tracks_to_points/.zgroup
intracktive/_tests/data/gt_data_bundle.zarr/tracks_to_points/data/.zarray
intracktive/_tests/data/gt_data_bundle.zarr/tracks_to_points/data/0.0
intracktive/_tests/data/gt_data_bundle.zarr/tracks_to_points/indices/.zarray
intracktive/_tests/data/gt_data_bundle.zarr/tracks_to_points/indices/0
intracktive/_tests/data/gt_data_bundle.zarr/tracks_to_points/indptr/.zarray
intracktive/_tests/data/gt_data_bundle.zarr/tracks_to_points/indptr/0
intracktive/_tests/data/gt_data_bundle.zarr/tracks_to_tracks/.zattrs
intracktive/_tests/data/gt_data_bundle.zarr/tracks_to_tracks/.zgroup
intracktive/_tests/data/gt_data_bundle.zarr/tracks_to_tracks/data/.zarray
intracktive/_tests/data/gt_data_bundle.zarr/tracks_to_tracks/data/0
intracktive-0.1.3.dist-info/METADATA
intracktive-0.1.3.dist-info/WHEEL
intracktive-0.1.3.dist-info/entry_points.txt
intracktive-0.1.3.dist-info/RECORD
