Metadata-Version: 2.4
Name: intracktive
Version: 0.1.3
Summary: Python tools for inTRACKtive
Project-URL: Documentation, https://github.com/royerlab/inTRACKtive/tree/main/python#readme
Project-URL: Issues, https://github.com/royerlab/inTRACKtive/issues
Project-URL: Source, https://github.com/royerlab/inTRACKtive
Author-email: Teun Huijben <teun.huijben@czbiohub.org>, Jordao Bragantini <jordao.bragantini@czbiohub.org>
License-Expression: MIT
Classifier: Programming Language :: Python
Classifier: Programming Language :: Python :: 3.10
Classifier: Programming Language :: Python :: 3.11
Classifier: Programming Language :: Python :: 3.12
Classifier: Programming Language :: Python :: Implementation :: CPython
Requires-Python: >=3.10
Requires-Dist: click
Requires-Dist: geff>=0.5
Requires-Dist: magicgui
Requires-Dist: pandas
Requires-Dist: pyarrow
Requires-Dist: scikit-image
Requires-Dist: scipy
Requires-Dist: zarr>=3
